ess/reduce/__init__.py
ess/reduce/logging.py
ess/reduce/normalization.py
ess/reduce/parameter.py
ess/reduce/py.typed
ess/reduce/streaming.py
ess/reduce/ui.py
ess/reduce/uncertainty.py
ess/reduce/workflow.py
ess/reduce/data/__init__.py
ess/reduce/data/_registry.py
ess/reduce/live/__init__.py
ess/reduce/live/raw.py
ess/reduce/live/roi.py
ess/reduce/live/workflow.py
ess/reduce/nexus/__init__.py
ess/reduce/nexus/_nexus_loader.py
ess/reduce/nexus/json_generator.py
ess/reduce/nexus/json_nexus.py
ess/reduce/nexus/types.py
ess/reduce/nexus/workflow.py
ess/reduce/scripts/grow_nexus.py
ess/reduce/time_of_flight/__init__.py
ess/reduce/time_of_flight/eto_to_tof.py
ess/reduce/time_of_flight/fakes.py
ess/reduce/time_of_flight/interpolator_numba.py
ess/reduce/time_of_flight/interpolator_scipy.py
ess/reduce/time_of_flight/lut.py
ess/reduce/time_of_flight/resample.py
ess/reduce/time_of_flight/types.py
ess/reduce/time_of_flight/workflow.py
ess/reduce/widgets/__init__.py
ess/reduce/widgets/_base.py
ess/reduce/widgets/_binedges_widget.py
ess/reduce/widgets/_bounds_widget.py
ess/reduce/widgets/_config.py
ess/reduce/widgets/_filename_widget.py
ess/reduce/widgets/_linspace_widget.py
ess/reduce/widgets/_optional_widget.py
ess/reduce/widgets/_spinner.py
ess/reduce/widgets/_string_widget.py
ess/reduce/widgets/_switchable_widget.py
ess/reduce/widgets/_vector_widget.py
essreduce-26.1.1.dist-info/licenses/LICENSE
essreduce-26.1.1.dist-info/METADATA
essreduce-26.1.1.dist-info/WHEEL
essreduce-26.1.1.dist-info/entry_points.txt
essreduce-26.1.1.dist-info/top_level.txt
essreduce-26.1.1.dist-info/RECORD
