Metadata-Version: 2.4
Name: essreduce
Version: 26.1.1
Summary: Common data reduction tools for the ESS facility
Author: Scipp contributors
License-Expression: BSD-3-Clause
Project-URL: Bug Tracker, https://github.com/scipp/essreduce/issues
Project-URL: Documentation, https://scipp.github.io/essreduce
Project-URL: Source, https://github.com/scipp/essreduce
Classifier: Intended Audience :: Science/Research
Classifier: Natural Language :: English
Classifier: Operating System :: OS Independent
Classifier: Programming Language :: Python :: 3
Classifier: Programming Language :: Python :: 3 :: Only
Classifier: Programming Language :: Python :: 3.11
Classifier: Programming Language :: Python :: 3.12
Classifier: Programming Language :: Python :: 3.13
Classifier: Topic :: Scientific/Engineering
Classifier: Typing :: Typed
Requires-Python: >=3.11
License-File: LICENSE
Requires-Dist: sciline>=25.11.0
Requires-Dist: scipp>=25.04.0
Requires-Dist: scippneutron>=25.11.1
Requires-Dist: scippnexus>=25.06.0
Provides-Extra: test
Requires-Dist: ipywidgets>=8.1; extra == "test"
Requires-Dist: matplotlib>=3.10.7; extra == "test"
Requires-Dist: numba>=0.59; extra == "test"
Requires-Dist: pooch>=1.5; extra == "test"
Requires-Dist: pytest>=7.0; extra == "test"
Requires-Dist: scipy>=1.14; extra == "test"
Requires-Dist: tof>=25.11.1; extra == "test"
Dynamic: license-file
